pygsf/__init__.py
pygsf/__main__.py
pygsf-0.1.1.dist-info/METADATA
pygsf-0.1.1.dist-info/WHEEL
pygsf-0.1.1.dist-info/licenses/LICENSE
pygsf-0.1.1.dist-info/RECORD
